manim/__init__.py
manim/__main__.py
manim/_config/__init__.py
manim/_config/cfg_subcmds.py
manim/_config/default.cfg
manim/_config/logger_utils.py
manim/_config/main_utils.py
manim/_config/utils.py
manim/animation/__init__.py
manim/animation/animation.py
manim/animation/composition.py
manim/animation/creation.py
manim/animation/fading.py
manim/animation/growing.py
manim/animation/indication.py
manim/animation/movement.py
manim/animation/numbers.py
manim/animation/rotation.py
manim/animation/transform.py
manim/animation/update.py
manim/camera/__init__.py
manim/camera/camera.py
manim/camera/js_camera.py
manim/camera/mapping_camera.py
manim/camera/moving_camera.py
manim/camera/multi_camera.py
manim/camera/three_d_camera.py
manim/constants.py
manim/container.py
manim/grpc/__init__.py
manim/grpc/gen/__init__.py
manim/grpc/gen/frameserver_pb2.py
manim/grpc/gen/frameserver_pb2_grpc.py
manim/grpc/gen/renderserver_pb2.py
manim/grpc/gen/renderserver_pb2_grpc.py
manim/grpc/impl/__init__.py
manim/grpc/impl/frame_server_impl.py
manim/grpc/proto/frameserver.proto
manim/grpc/proto/renderserver.proto
manim/grpc/update_protos.sh
manim/mobject/__init__.py
manim/mobject/changing.py
manim/mobject/coordinate_systems.py
manim/mobject/frame.py
manim/mobject/functions.py
manim/mobject/geometry.py
manim/mobject/logo.py
manim/mobject/matrix.py
manim/mobject/mobject.py
manim/mobject/mobject_update_utils.py
manim/mobject/number_line.py
manim/mobject/numbers.py
manim/mobject/probability.py
manim/mobject/shape_matchers.py
manim/mobject/svg/__init__.py
manim/mobject/svg/brace.py
manim/mobject/svg/code_mobject.py
manim/mobject/svg/svg_mobject.py
manim/mobject/svg/tex_mobject.py
manim/mobject/svg/text_mobject.py
manim/mobject/three_d_utils.py
manim/mobject/three_dimensions.py
manim/mobject/types/__init__.py
manim/mobject/types/image_mobject.py
manim/mobject/types/point_cloud_mobject.py
manim/mobject/types/vectorized_mobject.py
manim/mobject/value_tracker.py
manim/mobject/vector_field.py
manimce-0.1.1.post1.dist-info/entry_points.txt
manimce-0.1.1.post1.dist-info/LICENSE.community
manimce-0.1.1.post1.dist-info/LICENSE
manimce-0.1.1.post1.dist-info/WHEEL
manimce-0.1.1.post1.dist-info/METADATA
manimce-0.1.1.post1.dist-info/RECORD
