Metadata-Version: 2.1
Name: manimce
Version: 0.1.1.post1
Summary: [Deprecated] Animation engine for explanatory math videos.
Home-page: https://github.com/manimcommunity/manim
License: MIT
Author: The Manim Community Developers
Requires-Python: >=3.6,<4.0
Classifier: Development Status :: 4 - Beta
Classifier: License :: OSI Approved :: MIT License
Classifier: Natural Language :: English
Classifier: Programming Language :: Python :: 3
Classifier: Programming Language :: Python :: 3.6
Classifier: Programming Language :: Python :: 3.7
Classifier: Programming Language :: Python :: 3.8
Classifier: Programming Language :: Python :: 3.9
Classifier: Topic :: Multimedia :: Graphics
Classifier: Topic :: Multimedia :: Video
Classifier: Topic :: Scientific/Engineering
Provides-Extra: js_renderer
Requires-Dist: Pillow
Requires-Dist: cairocffi (>=1.1.0,<2.0.0)
Requires-Dist: colour
Requires-Dist: grpcio-tools; extra == "js_renderer"
Requires-Dist: grpcio; extra == "js_renderer"
Requires-Dist: numpy
Requires-Dist: pangocairocffi (>=0.4.0,<0.5.0)
Requires-Dist: pangocffi (>=0.8.0,<0.9.0)
Requires-Dist: progressbar
Requires-Dist: pycairo (>=1.19,<2.0)
Requires-Dist: pydub
Requires-Dist: pygments
Requires-Dist: rich (>=6.0,<7.0)
Requires-Dist: scipy
Requires-Dist: tqdm
Requires-Dist: watchdog; extra == "js_renderer"
Project-URL: Documentation, https://manimce.readthedocs.io/en/latest/
Project-URL: Repository, https://github.com/manimcommunity/manim
